codeocean/__init__.py
codeocean/capsule.py
codeocean/client.py
codeocean/components.py
codeocean/computation.py
codeocean/custom_metadata.py
codeocean/data_asset.py
codeocean/enum.py
codeocean/error.py
codeocean/pipeline.py
codeocean/models/__init__.py
codeocean/models/capsule.py
codeocean/models/components.py
codeocean/models/computation.py
codeocean/models/data_asset.py
codeocean/models/folder.py
codeocean-0.14.0.dist-info/METADATA
codeocean-0.14.0.dist-info/WHEEL
codeocean-0.14.0.dist-info/licenses/LICENSE
codeocean-0.14.0.dist-info/RECORD
