Metadata-Version: 2.4
Name: codeocean
Version: 0.14.0
Summary: Code Ocean Python SDK
Project-URL: Homepage, https://github.com/codeocean/codeocean-sdk-python
Project-URL: Issues, https://github.com/codeocean/codeocean-sdk-python/issues
Project-URL: Changelog, https://github.com/codeocean/codeocean-sdk-python/blob/main/CHANGELOG.md
Author-email: Code Ocean <dev@codeocean.com>
License-Expression: MIT
License-File: LICENSE
Classifier: License :: OSI Approved :: MIT License
Classifier: Operating System :: OS Independent
Classifier: Programming Language :: Python :: 3
Requires-Python: >=3.9
Requires-Dist: backports-strenum>=1.3.1; python_version < '3.11'
Requires-Dist: dataclasses-json
Requires-Dist: requests
Requires-Dist: requests-toolbelt
Provides-Extra: dev
Requires-Dist: flake8; extra == 'dev'
Requires-Dist: hatch; extra == 'dev'
